{
    "name": "Resizer",
    "script": "Resizer.js",
    "version": "0.0.9",
    "previousversions": [],
    "description": "Resizer lets you easily resize graphics and pages with a simple menu.\n\n### Commands\n\n* **!resizer [width] [height]** - Resizes the selected graphic(s).\n* **!resizer page [width] [height] [?pixels]** - Resizes the page (add pixels add the end to resize in pixels instead of units).\n\n* **!resizer** - Shows the Resizer menu (if there are graphics selected it also shows there current sizes).\n* **!resizer page** - Shows the pages current size.\n\n* **!resizer scale [amount] [up/down]** - Scale the entire page (with everything on it) by amount and up or down, eg. `!resizer scale 2 up`.\n* **!resizer fit [?keep_ratio]** - Makes the selected graphic fit the page (handy for maps), add `keep_ratio` to the end to keep the graphics ratio.\n\n* **!resizer center [?horizontal] [?vertical]** - Center the selected graphic(s), add `h`, `hor` or `horizontal` for horizontal and `v`, `ver` or `vertical` for vertical centering.\n\n* **!resizer help** - Shows the help menu.\n* **!resizer config** - Shows the config menu.\n* **!resizer menu** - Shows a menu to easily resize graphics/pages.\n\n![Resizer Menu](https://i.imgur.com/pRAuPPm.png \"Resizer Menu\")\n\nRoll20 Thread: https://app.roll20.net/forum/post/6285519/script-resizer/",
    "authors": "Robin Kuiper",
    "roll20userid": "1226016",
    "patreon": "https://www.patreon.com/robinkuiper",
    "useroptions": [],
    "dependencies": {},
    "modifies": {
        "state.RESIZER": "read,write",
        "page.width": "read,write",
        "page.height": "read,write",
        "page.scale_number": "read,write",
        "page.snapping_increment": "read,write",
        "graphic.name": "read",
        "graphic.width": "read,write",
        "graphic.height": "read,write",
        "graphic.top": "read,write",
        "graphic.left": "read,write",
        "text.name": "read",
        "text.font_size": "read,write",
        "text.width": "read,write",
        "text.height": "read,write",
        "path.name": "read",
        "path.scaleY": "read,write",
        "path.scaleX": "read,write",
        "path.top": "read,write",
        "path.left": "read,write"
    },
    "conflicts": []
}