{
  "name": "ManualAttribute",
  "version": "0.2.1",
  "description": "Creates a manual copy of an autocalculated field, and assigns it to the bar of a token.",
  "authors": "The Aaron",
  "roll20userid": "104025",
  "patreon": "https://www.patreon.com/shdwjk",
  "dependencies": [],
  "modifies": {
    "attribute": "create",
    "attribute.current": "write",
    "attribute.max": "read,write",
    "graphic.bar*_link": "write",
    "graphic.represents": "read"
  },
  "conflicts": [],
  "script": "ManualAttribute.js",
  "useroptions": {},
  "previousversions": []
}