{
  "name": "Tether",
  "script": "Tether",
  "version": "1.0.0",
  "description": "Tether creates persistent visual connections between tokens on the Roll20 VTT.\n\nKEY FEATURES:\n• Connect two selected tokens with a dynamic PathV2 line\n• Automatically redraws the connection when either token moves\n• Supports multiple simultaneous tethers\n• Automatically removes invalid tethers when tokens are deleted\n• Update existing tethers by running the command again with new options\n• Customize width, color, layer, and Dynamic Lighting barrier type\n• Stores tether data in campaign state for persistence across API restarts\n\nUSAGE:\n1. Select exactly two tokens\n2. Run !tether to create a connection\n3. Move either token and the tether updates automatically\n4. Select the same two tokens and run !untether to remove the connection\n\nOPTIONS:\n!tether width|5 color|blue layer|objects type|transparent\n\nSUPPORTED OPTIONS:\n• width - Line thickness (default: 5)\n• color - Named colors or hexadecimal values\n• layer - objects, gmlayer, map, walls, foreground\n• type - transparent, wall, or oneWay Dynamic Lighting barrier\n\nPERFECT FOR:\nVisualizing magical links, tethers, restraints, chains, leashes, spell effects, movable dynamic lighting barriers, and any other persistent connection between tokens.",
  "authors": "Keith Curtis",
  "roll20userid": "162065",
  "modifies": {
    "pathv2": "read,write"
  },
  "patreon": "https://www.patreon.com/c/KeithCurtis",
  "dependencies": [],
  "conflicts": [],
  "previousversions": ["1.0.0"]
}